pyreBloom
